{"nodes":[{"id":0,"text":"and","sentenceid":1,"rstweight":1.0,"pagerank":0.019391780309308871,"nosuffix":"and","label":"x7","hypernym":"and"},{"id":1,"text":"jump-06","sentenceid":1,"rstweight":1.0,"pagerank":0.019265766827640328,"nosuffix":"jump","label":"x3","hypernym":null},{"id":2,"text":"motel guest","sentenceid":1,"rstweight":1.0,"pagerank":0.013751709140368811,"nosuffix":"motel guest","label":"x2","hypernym":"motel guest"},{"id":4,"text":"window","sentenceid":1,"rstweight":1.0,"pagerank":0.010406088392180601,"nosuffix":"window","label":"x6","hypernym":"window"},{"id":5,"text":"lower-01","sentenceid":1,"rstweight":1.0,"pagerank":0.015441327097526868,"nosuffix":"lower","label":"x8","hypernym":null},{"id":7,"text":"ground","sentenceid":1,"rstweight":1.0,"pagerank":0.00917135654274212,"nosuffix":"ground","label":"x12","hypernym":"ground"},{"id":8,"text":"bedsheet","sentenceid":1,"rstweight":0.2,"pagerank":0.0041858852897956,"nosuffix":"bedsheet","label":"x14","hypernym":"bedsheet"},{"id":9,"text":"escape-01","sentenceid":1,"rstweight":0.16000000000000003,"pagerank":0.00583797951621593,"nosuffix":"escape","label":"x16","hypernym":"escape"},{"id":11,"text":"explode-01","sentenceid":1,"rstweight":0.0,"pagerank":0.00631481646327418,"nosuffix":"explode","label":"x20","hypernym":"explode"},{"id":12,"text":"cause-01","sentenceid":1,"rstweight":0.032000000000000008,"pagerank":0.0061348928056295165,"nosuffix":"cause","label":"x22","hypernym":"cause"},{"id":13,"text":"apparent","sentenceid":1,"rstweight":0.0,"pagerank":0.000569668596616424,"nosuffix":"apparent","label":"x21","hypernym":"apparent"},{"id":14,"text":"natural-gas leak-01","sentenceid":1,"rstweight":0.032000000000000008,"pagerank":0.0026485172651285168,"nosuffix":"natural leak","label":"x26","hypernym":"natural leak"},{"id":16,"text":"and","sentenceid":1,"rstweight":1.0,"pagerank":0.0086742917881851723,"nosuffix":"and","label":"x30","hypernym":null},{"id":17,"text":"kill-01","sentenceid":1,"rstweight":0.006400000000000002,"pagerank":0.0024333610782976546,"nosuffix":"kill","label":"x28","hypernym":null},{"id":18,"text":"injure-01","sentenceid":1,"rstweight":0.006400000000000002,"pagerank":0.0024333610782976546,"nosuffix":"injure","label":"x31","hypernym":null},{"id":19,"text":"person 10","sentenceid":1,"rstweight":0.0,"pagerank":0.00079084232128285746,"nosuffix":" 10","label":"x32","hypernym":null},{"id":20,"text":"4","sentenceid":1,"rstweight":0.0,"pagerank":0.00079084232128285746,"nosuffix":"4","label":"4","hypernym":null},{"id":23,"text":"investigate-01","sentenceid":2,"rstweight":1.0,"pagerank":0.014279384867630217,"nosuffix":"investigate","label":"x6","hypernym":"investigate"},{"id":24,"text":"report-01","sentenceid":2,"rstweight":1.0,"pagerank":0.016958986567704618,"nosuffix":"report","label":"x7","hypernym":"report"},{"id":25,"text":"gas leak-01","sentenceid":2,"rstweight":1.0,"pagerank":0.011743509498383216,"nosuffix":"gas leak","label":"x11","hypernym":"gas leak"},{"id":26,"text":"gas","sentenceid":2,"rstweight":1.0,"pagerank":0.0096388904664627441,"nosuffix":"gas","label":"x10","hypernym":"gas"},{"id":28,"text":"62-unit null_tag","sentenceid":2,"rstweight":0.0,"pagerank":0.00068410509158235992,"nosuffix":"62 null_tag","label":"x15","hypernym":"62 null_tag"},{"id":31,"text":"early","sentenceid":2,"rstweight":0.080000000000000016,"pagerank":0.0014994005620803711,"nosuffix":"early","label":"x22","hypernym":"early"},{"id":32,"text":"date-entity sunday","sentenceid":2,"rstweight":0.0,"pagerank":0.00048730516462527543,"nosuffix":" sunday","label":"xap1","hypernym":null},{"id":34,"text":"person have","sentenceid":2,"rstweight":0.0,"pagerank":0.0042488619077249894,"nosuffix":" have","label":"xap0","hypernym":null},{"id":42,"text":"just say-01","sentenceid":3,"rstweight":0.16000000000000003,"pagerank":0.0048124816562648224,"nosuffix":"just say","label":"x18","hypernym":"just say"},{"id":46,"text":"wife","sentenceid":3,"rstweight":0.16000000000000003,"pagerank":0.0027171489505182144,"nosuffix":"wife","label":"x17","hypernym":"wife"},{"id":47,"text":"come-01","sentenceid":3,"rstweight":0.16000000000000003,"pagerank":0.00288623536666118,"nosuffix":"come","label":"x13","hypernym":"come"},{"id":49,"text":"you","sentenceid":3,"rstweight":0.16000000000000003,"pagerank":0.0026047078797500484,"nosuffix":"you","label":"x22","hypernym":null},{"id":50,"text":"smell","sentenceid":3,"rstweight":0.16000000000000003,"pagerank":0.0038103942426914203,"nosuffix":"smell","label":"x23","hypernym":"smell"},{"id":51,"text":"gas","sentenceid":3,"rstweight":0.16000000000000003,"pagerank":0.0018226796394277354,"nosuffix":"gas","label":"x25","hypernym":null},{"id":53,"text":"say-01 named  Neal Woodrick","sentenceid":4,"rstweight":0.16000000000000003,"pagerank":0.00354708011867797,"nosuffix":" Neal Woodrick","label":"x1","hypernym":null},{"id":55,"text":"country named  Trenton","sentenceid":4,"rstweight":0.0,"pagerank":0.0011528009960816916,"nosuffix":" Trenton","label":"x8","hypernym":null},{"id":59,"text":"happen-01","sentenceid":4,"rstweight":0.4,"pagerank":0.0059214658516537335,"nosuffix":"happen","label":"x14","hypernym":null},{"id":60,"text":"then","sentenceid":4,"rstweight":0.4,"pagerank":0.0050094308823682918,"nosuffix":"then","label":"x12","hypernym":"then"},{"id":67,"text":"sound-01","sentenceid":5,"rstweight":0.4,"pagerank":0.00659180609804789,"nosuffix":"sound","label":"x2","hypernym":"sound"},{"id":68,"text":"it","sentenceid":5,"rstweight":0.4,"pagerank":0.0051811588392248554,"nosuffix":"it","label":"x1","hypernym":"it"},{"id":69,"text":"go-01","sentenceid":5,"rstweight":0.4,"pagerank":0.011632602988213133,"nosuffix":"go","label":"x8","hypernym":"go"},{"id":71,"text":"bomb","sentenceid":5,"rstweight":0.4,"pagerank":0.0037529342371739024,"nosuffix":"bomb","label":"x6","hypernym":"bomb"},{"id":72,"text":"boom-02","sentenceid":5,"rstweight":0.4,"pagerank":0.005416312168370999,"nosuffix":"boom","label":"x11","hypernym":"boom"},{"id":73,"text":"_","sentenceid":5,"rstweight":0.4,"pagerank":0.007677129195337154,"nosuffix":"_","label":"x10","hypernym":"_"},{"id":74,"text":"wife named  Joan Woodrick","sentenceid":5,"rstweight":1.0,"pagerank":0.0073868343662107858,"nosuffix":" Joan Woodrick","label":"x15","hypernym":null},{"id":79,"text":"comb","sentenceid":6,"rstweight":0.8,"pagerank":0.016720463740646958,"nosuffix":"comb","label":"x5","hypernym":"comb"},{"id":80,"text":"remains","sentenceid":6,"rstweight":0.8,"pagerank":0.019745232241356821,"nosuffix":"remains","label":"x8","hypernym":null},{"id":81,"text":"char","sentenceid":6,"rstweight":0.8,"pagerank":0.0092636047480923779,"nosuffix":"char","label":"x7","hypernym":null},{"id":82,"text":"motel","sentenceid":6,"rstweight":0.8,"pagerank":0.0092636047480923779,"nosuffix":"motel","label":"x11","hypernym":null},{"id":83,"text":"today","sentenceid":6,"rstweight":0.8,"pagerank":0.0077025465109519659,"nosuffix":"today","label":"x12","hypernym":"today"},{"id":85,"text":"person have","sentenceid":6,"rstweight":0.0,"pagerank":0.0027170752580054449,"nosuffix":" have","label":"xap0","hypernym":null},{"id":88,"text":"fire","sentenceid":6,"rstweight":1.0,"pagerank":0.011236271467301023,"nosuffix":"fire","label":"x1","hypernym":"fire"},{"id":89,"text":"say-01","sentenceid":7,"rstweight":1.0,"pagerank":0.037315234143378513,"nosuffix":"say","label":"x16","hypernym":"say"},{"id":90,"text":"believe-01","sentenceid":7,"rstweight":1.0,"pagerank":0.012227995844293821,"nosuffix":"believe","label":"x9","hypernym":"believe"},{"id":91,"text":"guest","sentenceid":7,"rstweight":1.0,"pagerank":0.024865219355210556,"nosuffix":"guest","label":"x7","hypernym":"guest"},{"id":92,"text":"all","sentenceid":7,"rstweight":1.0,"pagerank":0.0085407522072043687,"nosuffix":"all","label":"x1","hypernym":"all"},{"id":93,"text":"account","sentenceid":7,"rstweight":0.2,"pagerank":0.0038957668155028971,"nosuffix":"account","label":"x12","hypernym":"account"},{"id":94,"text":"authority","sentenceid":7,"rstweight":1.0,"pagerank":0.0073868343662107858,"nosuffix":"authority","label":"x15","hypernym":"authority"},{"id":95,"text":"50","sentenceid":7,"rstweight":1.0,"pagerank":0.0085407522072043687,"nosuffix":"50","label":"50","hypernym":null},{"id":96,"text":"use-01","sentenceid":8,"rstweight":1.0,"pagerank":0.031656343218590642,"nosuffix":"use","label":"x2","hypernym":"use"},{"id":97,"text":"firefighter","sentenceid":8,"rstweight":1.0,"pagerank":0.010326351842769756,"nosuffix":"firefighter","label":"x1","hypernym":"firefighter"},{"id":98,"text":"and","sentenceid":8,"rstweight":1.0,"pagerank":0.029800251372046026,"nosuffix":"and","label":"x8","hypernym":null},{"id":99,"text":"pitch","sentenceid":8,"rstweight":1.0,"pagerank":0.01107437973622369,"nosuffix":"pitch","label":"x6","hypernym":null},{"id":100,"text":"fork","sentenceid":8,"rstweight":1.0,"pagerank":0.019176005937257452,"nosuffix":"fork","label":"x7","hypernym":null},{"id":101,"text":"crane","sentenceid":8,"rstweight":1.0,"pagerank":0.012464040766945989,"nosuffix":"crane","label":"x4","hypernym":"crane"},{"id":102,"text":"shovel","sentenceid":8,"rstweight":1.0,"pagerank":0.01107437973622369,"nosuffix":"shovel","label":"x9","hypernym":null},{"id":103,"text":"sift","sentenceid":8,"rstweight":0.8,"pagerank":0.012102080817601224,"nosuffix":"sift","label":"x11","hypernym":"sift"},{"id":104,"text":"pile-02","sentenceid":8,"rstweight":0.8,"pagerank":0.012852591512600774,"nosuffix":"pile","label":"x13","hypernym":"pile"},{"id":105,"text":"leave-01","sentenceid":8,"rstweight":0.8,"pagerank":0.012104443948380613,"nosuffix":"leave","label":"x25","hypernym":"leave"},{"id":106,"text":"and","sentenceid":8,"rstweight":1.0,"pagerank":0.022629851658403123,"nosuffix":"and","label":"x29","hypernym":null},{"id":107,"text":"and","sentenceid":8,"rstweight":1.0,"pagerank":0.024720128152367696,"nosuffix":"and","label":"x22","hypernym":null},{"id":108,"text":"mattress","sentenceid":8,"rstweight":0.8,"pagerank":0.014308031675642256,"nosuffix":"mattress","label":"x16","hypernym":null},{"id":109,"text":"char","sentenceid":8,"rstweight":0.8,"pagerank":0.016324738279932607,"nosuffix":"char","label":"x15","hypernym":null},{"id":110,"text":"carpet","sentenceid":8,"rstweight":0.8,"pagerank":0.010291010998749562,"nosuffix":"carpet","label":"x18","hypernym":null},{"id":111,"text":"pink insulation","sentenceid":8,"rstweight":0.8,"pagerank":0.0090024919298392157,"nosuffix":"pink insulation","label":"x21","hypernym":null},{"id":113,"text":"wall","sentenceid":8,"rstweight":0.8,"pagerank":0.015522089234903377,"nosuffix":"wall","label":"x24","hypernym":null},{"id":114,"text":"dry","sentenceid":8,"rstweight":0.8,"pagerank":0.0100301500688405,"nosuffix":"dry","label":"x23","hypernym":null},{"id":115,"text":"fire","sentenceid":8,"rstweight":0.8,"pagerank":0.00792735186028488,"nosuffix":"fire","label":"x28","hypernym":null},{"id":116,"text":"explode","sentenceid":8,"rstweight":0.0,"pagerank":0.0029418806073383593,"nosuffix":"explode","label":"x30","hypernym":null},{"id":117,"text":"throw-06","sentenceid":8,"rstweight":0.16000000000000003,"pagerank":0.0063786783877385006,"nosuffix":"throw","label":"x33","hypernym":null},{"id":119,"text":"debris","sentenceid":8,"rstweight":0.16000000000000003,"pagerank":0.0018903560681473993,"nosuffix":"debris","label":"x34","hypernym":null},{"id":120,"text":"building","sentenceid":8,"rstweight":0.16000000000000003,"pagerank":0.0023791411835080724,"nosuffix":"building","label":"x42","hypernym":"building"},{"id":121,"text":"300","sentenceid":8,"rstweight":0.16000000000000003,"pagerank":0.0018903560681473993,"nosuffix":"300","label":"300","hypernym":null},{"id":123,"text":"almost positive","sentenceid":9,"rstweight":0.2,"pagerank":0.003342964794059264,"nosuffix":"almost positive","label":"x4","hypernym":"almost positive"},{"id":124,"text":"i","sentenceid":9,"rstweight":0.0,"pagerank":0.00072430901200412243,"nosuffix":"i","label":"x1","hypernym":null},{"id":126,"text":"gas natural explode-01","sentenceid":9,"rstweight":0.0,"pagerank":0.00072430901200412243,"nosuffix":"gas natural explode","label":"x10","hypernym":null},{"id":129,"text":"newspaper named  Gary Hawbaker","sentenceid":9,"rstweight":0.0,"pagerank":0.0027611149975608523,"nosuffix":" Gary Hawbaker","label":"x15","hypernym":null},{"id":132,"text":"country named  Hagerstown","sentenceid":9,"rstweight":0.0,"pagerank":0.0012172626974852961,"nosuffix":" Hagerstown","label":"x12","hypernym":null},{"id":134,"text":"chief","sentenceid":9,"rstweight":0.0,"pagerank":0.00059824156070630323,"nosuffix":"chief","label":"x14","hypernym":null},{"id":139,"text":"floor","sentenceid":10,"rstweight":0.2,"pagerank":0.0047161771410863182,"nosuffix":"floor","label":"x13","hypernym":null},{"id":140,"text":"whole building","sentenceid":10,"rstweight":0.2,"pagerank":0.0027791253277242435,"nosuffix":"whole building","label":"x6","hypernym":null},{"id":142,"text":"blow","sentenceid":10,"rstweight":0.2,"pagerank":0.0029097457444337261,"nosuffix":"blow","label":"x16","hypernym":null},{"id":143,"text":"engulf","sentenceid":11,"rstweight":0.040000000000000008,"pagerank":0.00071221013151024151,"nosuffix":"engulf","label":"x5","hypernym":"engulf"},{"id":144,"text":"whole that chunk","sentenceid":11,"rstweight":0.040000000000000008,"pagerank":0.00071221013151024151,"nosuffix":"whole that chunk","label":"x3","hypernym":null},{"id":148,"text":"newspaper named  Hawbaker","sentenceid":12,"rstweight":0.0,"pagerank":0.0011549953000276354,"nosuffix":" Hawbaker","label":"x1","hypernym":null},{"id":151,"text":"gas natural line","sentenceid":12,"rstweight":0.2,"pagerank":0.0018160364098530541,"nosuffix":"gas natural line","label":"x8","hypernym":"gas natural line"},{"id":155,"text":"possible","sentenceid":12,"rstweight":0.0,"pagerank":0.0014388757147168441,"nosuffix":"possible","label":"x18","hypernym":"possible"},{"id":156,"text":"put-01","sentenceid":12,"rstweight":0.2,"pagerank":0.00534896707779235,"nosuffix":"put","label":"x20","hypernym":null},{"id":157,"text":"we","sentenceid":12,"rstweight":0.2,"pagerank":0.0021155749313370503,"nosuffix":"we","label":"x17","hypernym":"we"},{"id":159,"text":"until","sentenceid":12,"rstweight":0.16000000000000003,"pagerank":0.0032079334175969068,"nosuffix":"until","label":"x27","hypernym":"until"},{"id":160,"text":"shut-05","sentenceid":12,"rstweight":0.16000000000000003,"pagerank":0.0041280987638966362,"nosuffix":"shut","label":"x31","hypernym":null},{"id":171,"text":"newspaper named  Joan Ganje-Fischer","sentenceid":14,"rstweight":0.0,"pagerank":0.0016093779471610748,"nosuffix":" Joan Ganje","label":"x1","hypernym":null},{"id":173,"text":"have-org-role-91","sentenceid":14,"rstweight":0.0,"pagerank":0.0062914522698383143,"nosuffix":"have","label":"x5","hypernym":"have"},{"id":174,"text":"spokeswoman","sentenceid":14,"rstweight":0.080000000000000016,"pagerank":0.00095292977242809147,"nosuffix":"spokeswoman","label":"s","hypernym":null},{"id":175,"text":"organization named  Inc.","sentenceid":14,"rstweight":0.0,"pagerank":0.00045438264713343947,"nosuffix":" Inc.","label":"x10","hypernym":null},{"id":183,"text":"tell-01","sentenceid":14,"rstweight":0.2,"pagerank":0.0051973508538819156,"nosuffix":"tell","label":"x37","hypernym":"tell"},{"id":184,"text":"after","sentenceid":14,"rstweight":0.2,"pagerank":0.0029086193806623591,"nosuffix":"after","label":"x18","hypernym":"after"},{"id":185,"text":"tell-01","sentenceid":14,"rstweight":0.2,"pagerank":0.0060713601088191816,"nosuffix":"tell","label":"x21","hypernym":null},{"id":188,"text":"clerk","sentenceid":14,"rstweight":0.2,"pagerank":0.0017007504603700695,"nosuffix":"clerk","label":"c1","hypernym":null},{"id":189,"text":"leak-01","sentenceid":14,"rstweight":0.2,"pagerank":0.0051525936212974662,"nosuffix":"leak","label":"x27","hypernym":"leak"},{"id":191,"text":"area","sentenceid":14,"rstweight":0.2,"pagerank":0.00511509948538238,"nosuffix":"area","label":"x32","hypernym":"area"},{"id":192,"text":"room","sentenceid":14,"rstweight":0.2,"pagerank":0.004827828196051479,"nosuffix":"room","label":"x31","hypernym":"room"},{"id":193,"text":"laundry","sentenceid":14,"rstweight":0.2,"pagerank":0.0022923972171987332,"nosuffix":"laundry","label":"x30","hypernym":null},{"id":194,"text":"gas company","sentenceid":14,"rstweight":0.2,"pagerank":0.0025043979312344387,"nosuffix":"gas company","label":"x36","hypernym":"gas company"},{"id":197,"text":"clerk","sentenceid":14,"rstweight":0.2,"pagerank":0.0017007504603700695,"nosuffix":"clerk","label":"c","hypernym":null},{"id":198,"text":"try-01","sentenceid":14,"rstweight":0.040000000000000008,"pagerank":0.0026878825542381735,"nosuffix":"try","label":"x41","hypernym":"try"},{"id":199,"text":"turn-02","sentenceid":14,"rstweight":0.040000000000000008,"pagerank":0.002920074285548249,"nosuffix":"turn","label":"x43","hypernym":"turn"},{"id":208,"text":"right-41","sentenceid":15,"rstweight":0.2,"pagerank":0.004927686569253284,"nosuffix":"right","label":"x3","hypernym":"right"},{"id":209,"text":"he","sentenceid":15,"rstweight":0.2,"pagerank":0.0023140331972668583,"nosuffix":"he","label":"x1","hypernym":null},{"id":210,"text":"happen-01","sentenceid":15,"rstweight":0.2,"pagerank":0.0031452368329988509,"nosuffix":"happen","label":"x12","hypernym":"happen"},{"id":213,"text":"she","sentenceid":15,"rstweight":0.080000000000000016,"pagerank":0.0016535424253222874,"nosuffix":"she","label":"x14","hypernym":"she"},{"id":215,"text":"come-01","sentenceid":16,"rstweight":0.2,"pagerank":0.00841106695254262,"nosuffix":"come","label":"x2","hypernym":null},{"id":216,"text":"he","sentenceid":16,"rstweight":0.2,"pagerank":0.0048422552692615134,"nosuffix":"he","label":"x1","hypernym":"he"},{"id":217,"text":"back","sentenceid":16,"rstweight":0.2,"pagerank":0.0030955931591094216,"nosuffix":"back","label":"x3","hypernym":"back"},{"id":218,"text":"front desk","sentenceid":16,"rstweight":0.2,"pagerank":0.0021575666995028251,"nosuffix":"front desk","label":"x7","hypernym":"front desk"},{"id":220,"text":"hair","sentenceid":16,"rstweight":0.2,"pagerank":0.0029274422571321321,"nosuffix":"hair","label":"x10","hypernym":"hair"},{"id":222,"text":"pull-06","sentenceid":17,"rstweight":0.2,"pagerank":0.0035068511082882864,"nosuffix":"pull","label":"x10","hypernym":"pull"},{"id":224,"text":"alarm-01","sentenceid":17,"rstweight":0.2,"pagerank":0.0031727140726773816,"nosuffix":"alarm","label":"x12","hypernym":"alarm"},{"id":225,"text":"notify-01","sentenceid":17,"rstweight":0.040000000000000008,"pagerank":0.0035893187393400104,"nosuffix":"notify","label":"x13","hypernym":"notify"},{"id":227,"text":"and","sentenceid":17,"rstweight":0.040000000000000008,"pagerank":0.0027229835290894294,"nosuffix":"and","label":"x19","hypernym":null},{"id":228,"text":"put-01","sentenceid":17,"rstweight":0.2,"pagerank":0.00473769591401599,"nosuffix":"put","label":"x2","hypernym":null},{"id":230,"text":"towel","sentenceid":17,"rstweight":0.2,"pagerank":0.0020162433708659374,"nosuffix":"towel","label":"x8","hypernym":"towel"},{"id":231,"text":"call-01","sentenceid":17,"rstweight":0.040000000000000008,"pagerank":0.001082454722722755,"nosuffix":"call","label":"x17","hypernym":null},{"id":232,"text":"911","sentenceid":17,"rstweight":0.040000000000000008,"pagerank":0.00060107133447084382,"nosuffix":"911","label":"x18","hypernym":null},{"id":233,"text":"begin-01","sentenceid":17,"rstweight":0.040000000000000008,"pagerank":0.0027333182158973774,"nosuffix":"begin","label":"x21","hypernym":null},{"id":235,"text":"evacuate","sentenceid":17,"rstweight":0.040000000000000008,"pagerank":0.0012722919522694962,"nosuffix":"evacuate","label":"x22","hypernym":"evacuate"},{"id":236,"text":"motel","sentenceid":17,"rstweight":0.040000000000000008,"pagerank":0.00066276843184815684,"nosuffix":"motel","label":"x24","hypernym":null},{"id":238,"text":"newspaper named  Donald Lee","sentenceid":18,"rstweight":0.0,"pagerank":0.00205900354048484,"nosuffix":" Donald Lee","label":"x1","hypernym":null},{"id":240,"text":"country named  Shorewood","sentenceid":18,"rstweight":0.0,"pagerank":0.00044611741726700019,"nosuffix":" Shorewood","label":"x7","hypernym":null},{"id":242,"text":"country named  Wis.","sentenceid":18,"rstweight":0.0,"pagerank":1.1098029260515465E-05,"nosuffix":" Wis.","label":"x9","hypernym":null},{"id":244,"text":"and","sentenceid":18,"rstweight":0.2,"pagerank":0.0055872592949253166,"nosuffix":"and","label":"x24","hypernym":null},{"id":245,"text":"awake","sentenceid":18,"rstweight":0.2,"pagerank":0.0021542974152151126,"nosuffix":"awake","label":"x13","hypernym":null},{"id":246,"text":"put-01","sentenceid":18,"rstweight":0.2,"pagerank":0.0032265288424973551,"nosuffix":"put","label":"x15","hypernym":null},{"id":247,"text":"and","sentenceid":18,"rstweight":0.2,"pagerank":0.0065983474873581626,"nosuffix":"and","label":"x21","hypernym":null},{"id":248,"text":"pants","sentenceid":18,"rstweight":0.2,"pagerank":0.0023185992405188724,"nosuffix":"pants","label":"x17","hypernym":null},{"id":249,"text":"shirt","sentenceid":18,"rstweight":0.2,"pagerank":0.0023185992405188724,"nosuffix":"shirt","label":"x20","hypernym":null},{"id":250,"text":"and","sentenceid":18,"rstweight":0.2,"pagerank":0.00396670456769966,"nosuffix":"and","label":"xap0","hypernym":null},{"id":251,"text":"coat","sentenceid":18,"rstweight":0.2,"pagerank":0.0025355467503139616,"nosuffix":"coat","label":"x23","hypernym":null},{"id":252,"text":"jump-01","sentenceid":18,"rstweight":0.2,"pagerank":0.0045352683400962292,"nosuffix":"jump","label":"x25","hypernym":null},{"id":253,"text":"distance-quantity","sentenceid":18,"rstweight":0.0,"pagerank":0.0018974698843700788,"nosuffix":"distance","label":"x27","hypernym":"distance"},{"id":254,"text":"foot","sentenceid":18,"rstweight":0.2,"pagerank":0.0054969960035529753,"nosuffix":"foot","label":"f","hypernym":"foot"},{"id":255,"text":"12-15","sentenceid":18,"rstweight":0.0,"pagerank":0.00041111845960989032,"nosuffix":"12","label":"x26","hypernym":null},{"id":256,"text":"second-story window","sentenceid":18,"rstweight":0.2,"pagerank":0.0019833488913091933,"nosuffix":"second window","label":"x32","hypernym":"second window"},{"id":258,"text":"break-01","sentenceid":18,"rstweight":0.2,"pagerank":0.0052359673731566993,"nosuffix":"break","label":"x34","hypernym":"break"},{"id":259,"text":"wrist","sentenceid":18,"rstweight":0.2,"pagerank":0.0019270435466258924,"nosuffix":"wrist","label":"x36","hypernym":"wrist"},{"id":260,"text":"fall","sentenceid":18,"rstweight":0.2,"pagerank":0.0019270435466258924,"nosuffix":"fall","label":"x39","hypernym":"fall"},{"id":261,"text":"39","sentenceid":18,"rstweight":0.080000000000000016,"pagerank":0.0009446645425616523,"nosuffix":"39","label":"39","hypernym":null},{"id":267,"text":"hear-01","sentenceid":19,"rstweight":0.006400000000000002,"pagerank":0.0021829929551739628,"nosuffix":"hear","label":"x2","hypernym":"hear"},{"id":268,"text":"i","sentenceid":19,"rstweight":0.0,"pagerank":0.00047298178946779748,"nosuffix":"i","label":"x1","hypernym":"i"},{"id":270,"text":"and","sentenceid":19,"rstweight":0.016000000000000004,"pagerank":0.0012668316189981021,"nosuffix":"and","label":"x4","hypernym":null},{"id":271,"text":"scream","sentenceid":19,"rstweight":0.016000000000000004,"pagerank":0.00037418959898286448,"nosuffix":"scream","label":"x3","hypernym":null},{"id":272,"text":"glass","sentenceid":19,"rstweight":0.016000000000000004,"pagerank":0.00037418959898286448,"nosuffix":"glass","label":"x5","hypernym":null},{"id":274,"text":"see-01","sentenceid":20,"rstweight":0.040000000000000008,"pagerank":0.000992777752306659,"nosuffix":"see","label":"x5","hypernym":"see"},{"id":275,"text":"number","sentenceid":20,"rstweight":0.040000000000000008,"pagerank":0.00057192632111203263,"nosuffix":"number","label":"x2","hypernym":"number"},{"id":276,"text":"flame","sentenceid":20,"rstweight":0.040000000000000008,"pagerank":0.00057192632111203263,"nosuffix":"flame","label":"x6","hypernym":"flame"},{"id":277,"text":"singe","sentenceid":21,"rstweight":0.0080000000000000019,"pagerank":0.00019855555153998835,"nosuffix":"singe","label":"x6","hypernym":"singe"},{"id":278,"text":"family","sentenceid":21,"rstweight":0.0080000000000000019,"pagerank":0.00011438526530106307,"nosuffix":"family","label":"x2","hypernym":null},{"id":279,"text":"hair","sentenceid":21,"rstweight":0.0080000000000000019,"pagerank":0.00011438526530106307,"nosuffix":"hair","label":"x5","hypernym":null},{"id":281,"text":"move-01","sentenceid":22,"rstweight":0.040000000000000008,"pagerank":0.0049156524890805872,"nosuffix":"move","label":"x4","hypernym":null},{"id":283,"text":"some","sentenceid":22,"rstweight":0.040000000000000008,"pagerank":0.0025581867036685441,"nosuffix":"some","label":"x1","hypernym":"some"},{"id":284,"text":"motel","sentenceid":22,"rstweight":0.040000000000000008,"pagerank":0.0017132324852568587,"nosuffix":"motel","label":"x7","hypernym":"motel"},{"id":285,"text":"across","sentenceid":22,"rstweight":0.040000000000000008,"pagerank":0.0012273874996119806,"nosuffix":"across","label":"x8","hypernym":"across"},{"id":286,"text":"street","sentenceid":22,"rstweight":0.040000000000000008,"pagerank":0.00064817448520434735,"nosuffix":"street","label":"x10","hypernym":null},{"id":287,"text":"provide-01","sentenceid":22,"rstweight":0.040000000000000008,"pagerank":0.0027070937412089942,"nosuffix":"provide","label":"x16","hypernym":null},{"id":288,"text":"organization named  Red Cross","sentenceid":22,"rstweight":0.0,"pagerank":0.00058653695553216264,"nosuffix":" Red Cross","label":"x14","hypernym":null},{"id":290,"text":"and","sentenceid":22,"rstweight":0.040000000000000008,"pagerank":0.0016978826677601811,"nosuffix":"and","label":"x20","hypernym":null},{"id":291,"text":"food","sentenceid":22,"rstweight":0.040000000000000008,"pagerank":0.00052517948595009762,"nosuffix":"food","label":"x17","hypernym":null},{"id":292,"text":"clothe","sentenceid":22,"rstweight":0.0,"pagerank":0.00027590592330277165,"nosuffix":"clothe","label":"x19","hypernym":null},{"id":293,"text":"shelter","sentenceid":22,"rstweight":0.040000000000000008,"pagerank":0.00052517948595009762,"nosuffix":"shelter","label":"x21","hypernym":null},{"id":296,"text":"identify-01","sentenceid":23,"rstweight":0.0080000000000000019,"pagerank":0.00010407898010324504,"nosuffix":"identify","label":"x4","hypernym":"identify"},{"id":297,"text":"die-01","sentenceid":23,"rstweight":0.0,"pagerank":8.39698623799035E-05,"nosuffix":"die","label":"x2","hypernym":"die"},{"id":298,"text":"dead","sentenceid":23,"rstweight":0.0080000000000000019,"pagerank":7.7144916812610549E-05,"nosuffix":"dead","label":"d","hypernym":null},{"id":299,"text":"and","sentenceid":23,"rstweight":0.0080000000000000019,"pagerank":0.0001243110658545613,"nosuffix":"and","label":"x34","hypernym":null},{"id":300,"text":"34 name","sentenceid":23,"rstweight":0.0,"pagerank":0.00018173942680530859,"nosuffix":"34 name","label":"x6","hypernym":null},{"id":301,"text":"city named  Milwaukee","sentenceid":23,"rstweight":0.0,"pagerank":3.41477820554539E-05,"nosuffix":" Milwaukee","label":"x13","hypernym":null},{"id":305,"text":"James","sentenceid":23,"rstweight":0.0080000000000000019,"pagerank":7.93873688019711E-05,"nosuffix":"James","label":"James","hypernym":null},{"id":306,"text":"G.","sentenceid":23,"rstweight":0.0080000000000000019,"pagerank":7.93873688019711E-05,"nosuffix":"G.","label":"G.","hypernym":null},{"id":307,"text":"Scharnek","sentenceid":23,"rstweight":0.0080000000000000019,"pagerank":7.93873688019711E-05,"nosuffix":"Scharnek","label":"Scharnek","hypernym":null},{"id":312,"text":"and","sentenceid":24,"rstweight":0.040000000000000008,"pagerank":0.0020815189930164773,"nosuffix":"and","label":"x15","hypernym":null},{"id":313,"text":"treat-01","sentenceid":24,"rstweight":0.040000000000000008,"pagerank":0.0010249619643476534,"nosuffix":"treat","label":"x4","hypernym":null},{"id":314,"text":"country named  Hospital","sentenceid":24,"rstweight":0.0,"pagerank":0.00022207508405883654,"nosuffix":" Hospital","label":"x8","hypernym":null},{"id":318,"text":"and","sentenceid":24,"rstweight":0.040000000000000008,"pagerank":0.00083235620284866974,"nosuffix":"and","label":"x12","hypernym":null},{"id":319,"text":"inhalation","sentenceid":24,"rstweight":0.040000000000000008,"pagerank":0.00075010484690118961,"nosuffix":"inhalation","label":"x11","hypernym":null},{"id":320,"text":"smoke","sentenceid":24,"rstweight":0.040000000000000008,"pagerank":0.00049305762890915509,"nosuffix":"smoke","label":"x10","hypernym":"smoke"},{"id":321,"text":"minor injure-01","sentenceid":24,"rstweight":0.0,"pagerank":0.00018034383727120028,"nosuffix":"minor injure","label":"x14","hypernym":null},{"id":323,"text":"release","sentenceid":24,"rstweight":0.040000000000000008,"pagerank":0.00070026932781418031,"nosuffix":"release","label":"x17","hypernym":null},{"id":324,"text":"person named  John Costopoulos","sentenceid":24,"rstweight":0.0,"pagerank":0.0016093779471610748,"nosuffix":" John Costopoulos","label":"x20","hypernym":null},{"id":327,"text":"spokesman","sentenceid":24,"rstweight":0.040000000000000008,"pagerank":0.00070365620978076544,"nosuffix":"spokesman","label":"s","hypernym":null}],"relations":[{"Head":0,"Tail":1,"conceptualrole":"op","label":"op1"},{"Head":0,"Tail":5,"conceptualrole":"op","label":"op2"},{"Head":1,"Tail":2,"conceptualrole":"agent","label":"ARG0"},{"Head":1,"Tail":4,"conceptualrole":"patient","label":"ARG1"},{"Head":5,"Tail":2,"conceptualrole":"agent","label":"ARG0"},{"Head":9,"Tail":11,"conceptualrole":"goal","label":"ARG2"},{"Head":11,"Tail":12,"conceptualrole":"ARG1-of","label":"ARG1-of"},{"Head":12,"Tail":13,"conceptualrole":"manner","label":"manner"},{"Head":12,"Tail":14,"conceptualrole":"cause","label":"ARG0"},{"Head":14,"Tail":16,"conceptualrole":"beneficiary","label":"beneficiary"},{"Head":16,"Tail":17,"conceptualrole":"op","label":"op1"},{"Head":16,"Tail":18,"conceptualrole":"op","label":"op2"},{"Head":17,"Tail":20,"conceptualrole":"patient","label":"ARG1"},{"Head":18,"Tail":19,"conceptualrole":"patient","label":"ARG1"},{"Head":23,"Tail":24,"conceptualrole":"stimulus","label":"ARG1"},{"Head":23,"Tail":34,"conceptualrole":"experiencer","label":"ARG0"},{"Head":24,"Tail":25,"conceptualrole":"topic","label":"ARG1"},{"Head":31,"Tail":32,"conceptualrole":"op","label":"op1"},{"Head":42,"Tail":46,"conceptualrole":"agent","label":"ARG0"},{"Head":42,"Tail":49,"conceptualrole":"agent","label":"ARG0"},{"Head":42,"Tail":50,"conceptualrole":"patient","label":"ARG1"},{"Head":46,"Tail":47,"conceptualrole":"patient-of","label":"ARG1-of"},{"Head":50,"Tail":49,"conceptualrole":"op","label":"ARG0"},{"Head":50,"Tail":51,"conceptualrole":"op","label":"ARG1"},{"Head":53,"Tail":55,"conceptualrole":"agent","label":"ARG0"},{"Head":59,"Tail":60,"conceptualrole":"time","label":"time"},{"Head":67,"Tail":68,"conceptualrole":"stimulus","label":"ARG1"},{"Head":67,"Tail":69,"conceptualrole":"time","label":"time"},{"Head":69,"Tail":68,"conceptualrole":"theme","label":"ARG1"},{"Head":69,"Tail":71,"conceptualrole":"theme","label":"ARG1"},{"Head":69,"Tail":72,"conceptualrole":"theme","label":"ARG1"},{"Head":72,"Tail":73,"conceptualrole":"ARG1-of","label":"ARG1-of"},{"Head":79,"Tail":80,"conceptualrole":"op","label":"ARG1"},{"Head":79,"Tail":83,"conceptualrole":"time","label":"time"},{"Head":79,"Tail":85,"conceptualrole":"op","label":"ARG1"},{"Head":80,"Tail":81,"conceptualrole":"mod-of","label":"ARG1-of"},{"Head":80,"Tail":82,"conceptualrole":"op","label":"ARG1"},{"Head":89,"Tail":90,"conceptualrole":"topic","label":"ARG1"},{"Head":89,"Tail":94,"conceptualrole":"agent","label":"ARG0"},{"Head":90,"Tail":91,"conceptualrole":"theme","label":"ARG1"},{"Head":90,"Tail":93,"conceptualrole":"theme","label":"ARG1"},{"Head":91,"Tail":92,"conceptualrole":"quant","label":"quant"},{"Head":91,"Tail":95,"conceptualrole":"quant","label":"quant"},{"Head":96,"Tail":97,"conceptualrole":"agent","label":"ARG0"},{"Head":96,"Tail":98,"conceptualrole":"asset","label":"ARG1"},{"Head":96,"Tail":103,"conceptualrole":"predicate","label":"ARG2"},{"Head":98,"Tail":99,"conceptualrole":"op","label":"op2"},{"Head":98,"Tail":100,"conceptualrole":"op","label":"op1"},{"Head":98,"Tail":102,"conceptualrole":"op","label":"op2"},{"Head":100,"Tail":101,"conceptualrole":"consist-of","label":"consist-of"},{"Head":103,"Tail":104,"conceptualrole":"instrument","label":"instrument"},{"Head":104,"Tail":105,"conceptualrole":"ARG1-of","label":"ARG1-of"},{"Head":105,"Tail":106,"conceptualrole":"goal","label":"ARG2"},{"Head":106,"Tail":107,"conceptualrole":"op","label":"op2"},{"Head":106,"Tail":115,"conceptualrole":"op","label":"op1"},{"Head":106,"Tail":116,"conceptualrole":"op","label":"op2"},{"Head":106,"Tail":117,"conceptualrole":"op","label":"op1"},{"Head":107,"Tail":108,"conceptualrole":"op","label":"op1"},{"Head":107,"Tail":111,"conceptualrole":"op","label":"op2"},{"Head":107,"Tail":113,"conceptualrole":"op","label":"op1"},{"Head":108,"Tail":109,"conceptualrole":"mod","label":"mod"},{"Head":109,"Tail":110,"conceptualrole":"op","label":"ARG1"},{"Head":110,"Tail":109,"conceptualrole":"patient-of","label":"ARG1-of"},{"Head":113,"Tail":114,"conceptualrole":"mod-of","label":"ARG1-of"},{"Head":117,"Tail":120,"conceptualrole":"goal","label":"ARG2"},{"Head":123,"Tail":124,"conceptualrole":"domain","label":"domain"},{"Head":123,"Tail":126,"conceptualrole":"domain","label":"domain"},{"Head":129,"Tail":134,"conceptualrole":"mod-of","label":"ARG0-of"},{"Head":139,"Tail":140,"conceptualrole":"op","label":"ARG3-of"},{"Head":143,"Tail":144,"conceptualrole":"op","label":"ARG1"},{"Head":155,"Tail":156,"conceptualrole":"domain","label":"domain"},{"Head":156,"Tail":157,"conceptualrole":"agent","label":"ARG0"},{"Head":156,"Tail":159,"conceptualrole":"time","label":"time"},{"Head":159,"Tail":160,"conceptualrole":"op","label":"op1"},{"Head":171,"Tail":173,"conceptualrole":"agent-of","label":"ARG0-of"},{"Head":173,"Tail":174,"conceptualrole":"op","label":"ARG2"},{"Head":173,"Tail":175,"conceptualrole":"op","label":"ARG1"},{"Head":183,"Tail":184,"conceptualrole":"time","label":"time"},{"Head":183,"Tail":194,"conceptualrole":"agent","label":"ARG0"},{"Head":183,"Tail":198,"conceptualrole":"topic","label":"ARG1"},{"Head":184,"Tail":185,"conceptualrole":"op","label":"op1"},{"Head":185,"Tail":189,"conceptualrole":"topic","label":"ARG1"},{"Head":189,"Tail":191,"conceptualrole":"beneficiary","label":"beneficiary"},{"Head":191,"Tail":192,"conceptualrole":"location-of","label":"location-of"},{"Head":192,"Tail":193,"conceptualrole":"op","label":"ARG1"},{"Head":198,"Tail":194,"conceptualrole":"agent","label":"ARG0"},{"Head":198,"Tail":199,"conceptualrole":"theme","label":"ARG1"},{"Head":208,"Tail":209,"conceptualrole":"op","label":"ARG1"},{"Head":208,"Tail":210,"conceptualrole":"time","label":"time"},{"Head":215,"Tail":216,"conceptualrole":"theme","label":"ARG1"},{"Head":215,"Tail":217,"conceptualrole":"direction","label":"direction"},{"Head":215,"Tail":218,"conceptualrole":"extend","label":"ARG2"},{"Head":215,"Tail":220,"conceptualrole":"theme","label":"ARG1"},{"Head":222,"Tail":224,"conceptualrole":"patient","label":"ARG1"},{"Head":222,"Tail":227,"conceptualrole":"patient","label":"ARG1"},{"Head":224,"Tail":225,"conceptualrole":"ARG1-of","label":"ARG1-of"},{"Head":227,"Tail":228,"conceptualrole":"op","label":"op1"},{"Head":227,"Tail":231,"conceptualrole":"op","label":"op2"},{"Head":227,"Tail":233,"conceptualrole":"op","label":"op2"},{"Head":228,"Tail":230,"conceptualrole":"destination","label":"ARG2"},{"Head":231,"Tail":232,"conceptualrole":"result","label":"ARG2"},{"Head":233,"Tail":235,"conceptualrole":"theme","label":"ARG1"},{"Head":235,"Tail":236,"conceptualrole":"op","label":"ARG1"},{"Head":238,"Tail":261,"conceptualrole":"quant","label":"quant"},{"Head":238,"Tail":240,"conceptualrole":"source","label":"source"},{"Head":244,"Tail":245,"conceptualrole":"op","label":"op1"},{"Head":244,"Tail":246,"conceptualrole":"op","label":"op2"},{"Head":244,"Tail":252,"conceptualrole":"op","label":"op2"},{"Head":246,"Tail":247,"conceptualrole":"theme","label":"ARG1"},{"Head":247,"Tail":248,"conceptualrole":"op","label":"op1"},{"Head":247,"Tail":249,"conceptualrole":"op","label":"op2"},{"Head":247,"Tail":250,"conceptualrole":"op","label":"op1"},{"Head":250,"Tail":251,"conceptualrole":"op","label":"op1"},{"Head":252,"Tail":253,"conceptualrole":"patient","label":"ARG1"},{"Head":252,"Tail":256,"conceptualrole":"patient","label":"ARG1"},{"Head":252,"Tail":258,"conceptualrole":"extent","label":"ARG2"},{"Head":253,"Tail":254,"conceptualrole":"unit","label":"unit"},{"Head":253,"Tail":255,"conceptualrole":"quant","label":"quant"},{"Head":258,"Tail":259,"conceptualrole":"patient","label":"ARG1"},{"Head":258,"Tail":260,"conceptualrole":"time","label":"time"},{"Head":267,"Tail":268,"conceptualrole":"experiencer","label":"ARG0"},{"Head":270,"Tail":271,"conceptualrole":"op","label":"op1"},{"Head":270,"Tail":272,"conceptualrole":"op","label":"op2"},{"Head":274,"Tail":275,"conceptualrole":"agent","label":"ARG0"},{"Head":274,"Tail":276,"conceptualrole":"theme","label":"ARG1"},{"Head":277,"Tail":278,"conceptualrole":"op","label":"ARG0"},{"Head":277,"Tail":279,"conceptualrole":"op","label":"ARG0"},{"Head":281,"Tail":284,"conceptualrole":"destination","label":"ARG2"},{"Head":284,"Tail":285,"conceptualrole":"location","label":"location"},{"Head":285,"Tail":286,"conceptualrole":"op","label":"op1"},{"Head":287,"Tail":288,"conceptualrole":"agent","label":"ARG0"},{"Head":287,"Tail":290,"conceptualrole":"theme","label":"ARG1"},{"Head":290,"Tail":291,"conceptualrole":"op","label":"op1"},{"Head":290,"Tail":292,"conceptualrole":"op","label":"op2"},{"Head":290,"Tail":293,"conceptualrole":"op","label":"op2"},{"Head":296,"Tail":297,"conceptualrole":"theme","label":"ARG1"},{"Head":296,"Tail":299,"conceptualrole":"attribute","label":"ARG2"},{"Head":297,"Tail":298,"conceptualrole":"op","label":"op"},{"Head":299,"Tail":300,"conceptualrole":"op","label":"op1"},{"Head":299,"Tail":301,"conceptualrole":"op","label":"op1"},{"Head":300,"Tail":305,"conceptualrole":"op","label":"op1"},{"Head":300,"Tail":306,"conceptualrole":"op","label":"op2"},{"Head":300,"Tail":307,"conceptualrole":"op","label":"op3"},{"Head":312,"Tail":313,"conceptualrole":"op","label":"op1"},{"Head":312,"Tail":323,"conceptualrole":"op","label":"op2"},{"Head":313,"Tail":314,"conceptualrole":"location","label":"location"},{"Head":313,"Tail":318,"conceptualrole":"theme","label":"ARG1"},{"Head":318,"Tail":319,"conceptualrole":"op","label":"op1"},{"Head":318,"Tail":321,"conceptualrole":"op","label":"op2"},{"Head":319,"Tail":320,"conceptualrole":"consist-of","label":"consist-of"},{"Head":0,"Tail":53,"conceptualrole":"op","label":"op2"},{"Head":0,"Tail":59,"conceptualrole":"op","label":"op2"},{"Head":0,"Tail":215,"conceptualrole":"op","label":"op1"},{"Head":0,"Tail":281,"conceptualrole":"op","label":"op1"},{"Head":0,"Tail":287,"conceptualrole":"op","label":"op2"},{"Head":5,"Tail":96,"conceptualrole":"goal","label":"ARG2"},{"Head":96,"Tail":7,"conceptualrole":"predicate","label":"ARG2"},{"Head":96,"Tail":8,"conceptualrole":"asset","label":"ARG1"},{"Head":96,"Tail":9,"conceptualrole":"predicate","label":"ARG2"},{"Head":9,"Tail":88,"conceptualrole":"location","label":"ARG1"},{"Head":129,"Tail":88,"conceptualrole":"agent-of","label":"ARG0-of"},{"Head":88,"Tail":132,"conceptualrole":"op","label":"ARG1"},{"Head":156,"Tail":88,"conceptualrole":"theme","label":"ARG1"},{"Head":215,"Tail":88,"conceptualrole":"goal","label":"ARG4"},{"Head":28,"Tail":11,"conceptualrole":"time","label":"time"},{"Head":11,"Tail":31,"conceptualrole":"time","label":"time"},{"Head":79,"Tail":11,"conceptualrole":"time","label":"time"},{"Head":12,"Tail":151,"conceptualrole":"theme","label":"ARG1"},{"Head":12,"Tail":155,"conceptualrole":"theme","label":"ARG1"},{"Head":12,"Tail":88,"conceptualrole":"op2","label":"op2"},{"Head":89,"Tail":23,"conceptualrole":"topic","label":"ARG1"},{"Head":89,"Tail":67,"conceptualrole":"topic","label":"ARG1"},{"Head":89,"Tail":74,"conceptualrole":"agent","label":"ARG0"},{"Head":89,"Tail":123,"conceptualrole":"topic","label":"ARG1"},{"Head":89,"Tail":129,"conceptualrole":"agent","label":"ARG0"},{"Head":89,"Tail":148,"conceptualrole":"agent","label":"ARG0"},{"Head":89,"Tail":12,"conceptualrole":"topic","label":"ARG1"},{"Head":89,"Tail":171,"conceptualrole":"agent","label":"ARG0"},{"Head":89,"Tail":183,"conceptualrole":"topic","label":"ARG1"},{"Head":89,"Tail":208,"conceptualrole":"topic","label":"ARG1"},{"Head":89,"Tail":213,"conceptualrole":"agent","label":"ARG0"},{"Head":89,"Tail":238,"conceptualrole":"agent","label":"ARG0"},{"Head":89,"Tail":244,"conceptualrole":"topic","label":"ARG1"},{"Head":89,"Tail":267,"conceptualrole":"topic","label":"ARG1"},{"Head":89,"Tail":312,"conceptualrole":"topic","label":"ARG1"},{"Head":89,"Tail":324,"conceptualrole":"agent","label":"ARG0"},{"Head":160,"Tail":26,"conceptualrole":"patient","label":"ARG1"},{"Head":189,"Tail":26,"conceptualrole":"theme","label":"ARG1"},{"Head":199,"Tail":26,"conceptualrole":"patient","label":"ARG1"},{"Head":42,"Tail":69,"conceptualrole":"patient","label":"ARG1"},{"Head":69,"Tail":192,"conceptualrole":"goal","label":"ARG4"},{"Head":47,"Tail":217,"conceptualrole":"direction","label":"direction"},{"Head":233,"Tail":60,"conceptualrole":"time","label":"time"},{"Head":73,"Tail":139,"conceptualrole":"op","label":"ARG1"},{"Head":73,"Tail":142,"conceptualrole":"op","label":"ARG1"},{"Head":185,"Tail":91,"conceptualrole":"agent","label":"ARG0"},{"Head":225,"Tail":91,"conceptualrole":"recipient","label":"ARG1"},{"Head":281,"Tail":91,"conceptualrole":"theme","label":"ARG1"},{"Head":91,"Tail":283,"conceptualrole":"quant","label":"quant"},{"Head":89,"Tail":97,"conceptualrole":"topic","label":"ARG1"},{"Head":117,"Tail":254,"conceptualrole":"extent","label":"extent"},{"Head":254,"Tail":119,"conceptualrole":"op","label":"ARG1"},{"Head":254,"Tail":121,"conceptualrole":"quant","label":"quant"},{"Head":89,"Tail":216,"conceptualrole":"agent","label":"ARG0"},{"Head":222,"Tail":216,"conceptualrole":"agent","label":"ARG0"},{"Head":228,"Tail":216,"conceptualrole":"agent","label":"ARG0"},{"Head":185,"Tail":173,"conceptualrole":"recipient","label":"ARG2"},{"Head":173,"Tail":188,"conceptualrole":"op","label":"ARG2"},{"Head":183,"Tail":173,"conceptualrole":"recipient","label":"ARG2"},{"Head":173,"Tail":197,"conceptualrole":"op","label":"ARG2"},{"Head":324,"Tail":173,"conceptualrole":"agent-of","label":"ARG0-of"},{"Head":173,"Tail":327,"conceptualrole":"op","label":"ARG2"},{"Head":210,"Tail":191,"conceptualrole":"location","label":"location"},{"Head":191,"Tail":11,"conceptualrole":"part-of","label":"part-of"},{"Head":228,"Tail":220,"conceptualrole":"theme","label":"ARG1"},{"Head":267,"Tail":258,"conceptualrole":"stimulus","label":"ARG1"},{"Head":258,"Tail":270,"conceptualrole":"patient","label":"ARG1"},{"Head":89,"Tail":34,"conceptualrole":"agent","label":"ARG0"},{"Head":301,"Tail":242,"conceptualrole":"location","label":"location"}]}